[{"spell_name": "Blood in the Water", "casting_time": "1 swift action", "spell_level": 1, "rulebook": "ToB", "duration": "Stance", "effect": "", "spell_range": "Personal", "components": "", "spell_school": "Tiger Claw"}, {"spell_name": "Bolstering Voice", "casting_time": "1 swift action", "spell_level": 1, "rulebook": "ToB", "duration": "Stance", "effect": "", "spell_range": "Personal", "components": "", "spell_school": "White Raven"}, {"spell_name": "Charging Minotaur", "casting_time": "1 full-round action", "spell_level": 1, "rulebook": "ToB", "duration": "", "effect": "", "spell_range": "Melee attack", "components": "", "spell_school": "Stone Dragon"}, {"spell_name": "Douse the Flames", "casting_time": "1 standard action", "spell_level": 1, "rulebook": "ToB", "duration": "1 round", "effect": "", "spell_range": "Melee attack", "components": "", "spell_school": "White Raven"}, {"spell_name": "Hunter's Sense", "casting_time": "1 swift action", "spell_level": 1, "rulebook": "ToB", "duration": "Stance", "effect": "", "spell_range": "Personal", "components": "", "spell_school": "Tiger Claw"}, {"spell_name": "Leading the Attack", "casting_time": "1 standard action", "spell_level": 1, "rulebook": "ToB", "duration": "1 round", "effect": "", "spell_range": "Melee attack", "components": "", "spell_school": "White Raven"}, {"spell_name": "Leading the Charge", "casting_time": "1 swift action", "spell_level": 1, "rulebook": "ToB", "duration": "Stance", "effect": "", "spell_range": "60 ft.", "components": "", "spell_school": "White Raven"}, {"spell_name": "Moment of Perfect Mind", "casting_time": "1 immediate action", "spell_level": 1, "rulebook": "ToB", "duration": "", "effect": "", "spell_range": "Personal", "components": "", "spell_school": "Diamond Mind"}, {"spell_name": "Punishing Stance", "casting_time": "1 swift action", "spell_level": 1, "rulebook": "ToB", "duration": "Stance", "effect": "", "spell_range": "Personal", "components": "", "spell_school": "Iron Heart"}, {"spell_name": "Sapphire Nightmare Blade", "casting_time": "1 standard action", "spell_level": 1, "rulebook": "ToB", "duration": "", "effect": "", "spell_range": "Melee attack", "components": "", "spell_school": "Diamond Mind"}, {"spell_name": "Stance of Clarity", "casting_time": "1 swift action", "spell_level": 1, "rulebook": "ToB", "duration": "Stance", "effect": "", "spell_range": "Personal", "components": "", "spell_school": "Diamond Mind"}, {"spell_name": "Steel Wind", "casting_time": "1 standard action", "spell_level": 1, "rulebook": "ToB", "duration": "", "effect": "", "spell_range": "Melee attack", "components": "", "spell_school": "Iron Heart"}, {"spell_name": "Steely Strike", "casting_time": "1 standard action", "spell_level": 1, "rulebook": "ToB", "duration": "1 round; see text", "effect": "", "spell_range": "Melee attack", "components": "", "spell_school": "Iron Heart"}, {"spell_name": "Stone Bones", "casting_time": "1 standard action", "spell_level": 1, "rulebook": "ToB", "duration": "1 round", "effect": "", "spell_range": "Personal", "components": "", "spell_school": "Stone Dragon"}, {"spell_name": "Stonefoot Stance", "casting_time": "1 swift action", "spell_level": 1, "rulebook": "ToB", "duration": "Stance", "effect": "", "spell_range": "Personal", "components": "", "spell_school": "Stone Dragon"}, {"spell_name": "Sudden Leap", "casting_time": "1 swift action", "spell_level": 1, "rulebook": "ToB", "duration": "Instantaneous", "effect": "", "spell_range": "Personal", "components": "", "spell_school": "Tiger Claw"}, {"spell_name": "Wolf Fang Strike", "casting_time": "1 standard action", "spell_level": 1, "rulebook": "ToB", "duration": "", "effect": "", "spell_range": "Melee attack", "components": "", "spell_school": "Tiger Claw"}, {"spell_name": "Action Before Thought", "casting_time": "1 immediate action", "spell_level": 2, "rulebook": "ToB", "duration": "", "effect": "", "spell_range": "Personal", "components": "", "spell_school": "Diamond Mind"}, {"spell_name": "Battle Leader's Charge", "casting_time": "1 full-round action", "spell_level": 2, "rulebook": "ToB", "duration": "", "effect": "", "spell_range": "Melee attack", "components": "", "spell_school": "White Raven"}, {"spell_name": "Claw at the Moon", "casting_time": "1 standard action", "spell_level": 2, "rulebook": "ToB", "duration": "", "effect": "", "spell_range": "Melee attack", "components": "", "spell_school": "Tiger Claw"}, {"spell_name": "Disarming Strike", "casting_time": "1 standard action", "spell_level": 2, "rulebook": "ToB", "duration": "", "effect": "", "spell_range": "Melee attack", "components": "", "spell_school": "Iron Heart"}, {"spell_name": "Emerald Razor", "casting_time": "1 standard action", "spell_level": 2, "rulebook": "ToB", "duration": "", "effect": "", "spell_range": "Melee attack", "components": "", "spell_school": "Diamond Mind"}, {"spell_name": "Mountain Hammer", "casting_time": "1 standard action", "spell_level": 2, "rulebook": "ToB", "duration": "", "effect": "", "spell_range": "Melee attack", "components": "", "spell_school": "Stone Dragon"}, {"spell_name": "Rabid Wolf Strike", "casting_time": "1 standard action", "spell_level": 2, "rulebook": "ToB", "duration": "", "effect": "", "spell_range": "Melee attack", "components": "", "spell_school": "Tiger Claw"}, {"spell_name": "Stone Vise", "casting_time": "1 standard action", "spell_level": 2, "rulebook": "ToB", "duration": "1 round", "effect": "", "spell_range": "Melee attack", "components": "", "spell_school": "Stone Dragon"}, {"spell_name": "Tactical Strike", "casting_time": "1 standard action", "spell_level": 2, "rulebook": "ToB", "duration": "", "effect": "", "spell_range": "Melee attack", "components": "", "spell_school": "White Raven"}, {"spell_name": "Wall of Blades", "casting_time": "1 immediate action", "spell_level": 2, "rulebook": "ToB", "duration": "", "effect": "", "spell_range": "Personal", "components": "", "spell_school": "Iron Heart"}, {"spell_name": "Absolute Steel", "casting_time": "1 swift action", "spell_level": 3, "rulebook": "ToB", "duration": "Stance", "effect": "", "spell_range": "Personal", "components": "", "spell_school": "Iron Heart"}, {"spell_name": "Bonecrusher", "casting_time": "1 standard action", "spell_level": 3, "rulebook": "ToB", "duration": "See text", "effect": "", "spell_range": "Melee attack", "components": "", "spell_school": "Stone Dragon"}, {"spell_name": "Crushing Weight of the Mountain", "casting_time": "1 swift action", "spell_level": 3, "rulebook": "ToB", "duration": "Stance", "effect": "", "spell_range": "Personal", "components": "", "spell_school": "Stone Dragon"}, {"spell_name": "Exorcism of Steel", "casting_time": "Standard Action", "spell_level": 3, "rulebook": "ToB", "duration": "1 minute", "effect": "", "spell_range": "Melee attack", "components": "", "spell_school": "Iron Heart"}, {"spell_name": "Flesh Ripper", "casting_time": "1 standard action", "spell_level": 3, "rulebook": "ToB", "duration": "1 round or more; see text", "effect": "", "spell_range": "Melee attack", "components": "", "spell_school": "Tiger Claw"}, {"spell_name": "Insightful Strike", "casting_time": "1 standard action", "spell_level": 3, "rulebook": "ToB", "duration": "", "effect": "", "spell_range": "Melee attack", "components": "", "spell_school": "Diamond Mind"}, {"spell_name": "Iron Heart Surge", "casting_time": "1 standard action", "spell_level": 3, "rulebook": "ToB", "duration": "See text", "effect": "", "spell_range": "Personal", "components": "", "spell_school": "Iron Heart"}, {"spell_name": "Leaping Dragon Stance", "casting_time": "1 swift action", "spell_level": 3, "rulebook": "ToB", "duration": "Stance", "effect": "", "spell_range": "Personal", "components": "", "spell_school": "Tiger Claw"}, {"spell_name": "Lion's Roar", "casting_time": "1 swift action", "spell_level": 3, "rulebook": "ToB", "duration": "1 round", "effect": "", "spell_range": "60 ft.", "components": "", "spell_school": "White Raven"}, {"spell_name": "Mind Over Body", "casting_time": "1 immediate action", "spell_level": 3, "rulebook": "ToB", "duration": "", "effect": "", "spell_range": "Personal", "components": "", "spell_school": "Diamond Mind"}, {"spell_name": "Pearl of Black Doubt", "casting_time": "1 swift action", "spell_level": 3, "rulebook": "ToB", "duration": "Stance", "effect": "", "spell_range": "Personal", "components": "", "spell_school": "Diamond Mind"}, {"spell_name": "Roots of the Mountain", "casting_time": "1 swift action", "spell_level": 3, "rulebook": "ToB", "duration": "Stance", "effect": "", "spell_range": "Personal", "components": "", "spell_school": "Stone Dragon"}, {"spell_name": "Soaring Raptor Strike", "casting_time": "1 standard action", "spell_level": 3, "rulebook": "ToB", "duration": "", "effect": "", "spell_range": "Melee attack", "components": "", "spell_school": "Tiger Claw"}, {"spell_name": "Stone Dragon's Fury", "casting_time": "1 standard action", "spell_level": 3, "rulebook": "ToB", "duration": "", "effect": "", "spell_range": "Melee attack", "components": "", "spell_school": "Stone Dragon"}, {"spell_name": "Tactics of the Wolf", "casting_time": "1 swift action", "spell_level": 3, "rulebook": "ToB", "duration": "Stance", "effect": "", "spell_range": "Personal", "components": "", "spell_school": "White Raven"}, {"spell_name": "White Raven Tactics", "casting_time": "1 swift action", "spell_level": 3, "rulebook": "ToB", "duration": "", "effect": "", "spell_range": "10 ft.", "components": "", "spell_school": "White Raven"}, {"spell_name": "Wolverine Stance", "casting_time": "1 swift action", "spell_level": 3, "rulebook": "ToB", "duration": "Stance", "effect": "", "spell_range": "Personal", "components": "", "spell_school": "Tiger Claw"}, {"spell_name": "Bonesplitting Strike", "casting_time": "1 standard action", "spell_level": 4, "rulebook": "ToB", "duration": "", "effect": "", "spell_range": "Melee attack", "components": "", "spell_school": "Stone Dragon"}, {"spell_name": "Boulder Roll", "casting_time": "1 full-round action", "spell_level": 4, "rulebook": "ToB", "duration": "Instantaneous", "effect": "", "spell_range": "Personal", "components": "", "spell_school": "Stone Dragon"}, {"spell_name": "Bounding Assault", "casting_time": "1 full-round action", "spell_level": 4, "rulebook": "ToB", "duration": "", "effect": "", "spell_range": "Melee attack", "components": "", "spell_school": "Diamond Mind"}, {"spell_name": "Covering Strike", "casting_time": "1 swift action", "spell_level": 4, "rulebook": "ToB", "duration": "3 rounds", "effect": "", "spell_range": "Personal", "components": "", "spell_school": "White Raven"}, {"spell_name": "Death from Above", "casting_time": "1 standard action", "spell_level": 4, "rulebook": "ToB", "duration": "", "effect": "", "spell_range": "Melee attack", "components": "", "spell_school": "Tiger Claw"}, {"spell_name": "Fountain of Blood", "casting_time": "1 swift action", "spell_level": 4, "rulebook": "ToB", "duration": "1 minute", "effect": "", "spell_range": "30 ft.", "components": "", "spell_school": "Tiger Claw"}, {"spell_name": "Lightning Recovery", "casting_time": "1 immediate action", "spell_level": 4, "rulebook": "ToB", "duration": "", "effect": "", "spell_range": "Personal", "components": "", "spell_school": "Iron Heart"}, {"spell_name": "Mind Strike", "casting_time": "1 standard action", "spell_level": 4, "rulebook": "ToB", "duration": "", "effect": "", "spell_range": "Melee attack", "components": "", "spell_school": "Diamond Mind"}, {"spell_name": "Mithral Tornado", "casting_time": "1 standard action", "spell_level": 4, "rulebook": "ToB", "duration": "", "effect": "", "spell_range": "Melee attack", "components": "", "spell_school": "Iron Heart"}, {"spell_name": "Overwhelming Mountain Strike", "casting_time": "1 standard action", "spell_level": 4, "rulebook": "ToB", "duration": "1 round", "effect": "", "spell_range": "Melee attack", "components": "", "spell_school": "Stone Dragon"}, {"spell_name": "Ruby Nightmare Blade", "casting_time": "1 standard action", "spell_level": 4, "rulebook": "ToB", "duration": "", "effect": "", "spell_range": "Melee attack", "components": "", "spell_school": "Diamond Mind"}, {"spell_name": "White Raven Strike", "casting_time": "1 standard action", "spell_level": 4, "rulebook": "ToB", "duration": "", "effect": "", "spell_range": "Melee attack", "components": "", "spell_school": "White Raven"}, {"spell_name": "Dancing Blade Form", "casting_time": "1 swift action", "spell_level": 5, "rulebook": "ToB", "duration": "Stance", "effect": "", "spell_range": "Personal", "components": "", "spell_school": "Iron Heart"}, {"spell_name": "Dancing Mongoose", "casting_time": "1 swift action", "spell_level": 5, "rulebook": "ToB", "duration": "End of turn", "effect": "", "spell_range": "Personal", "components": "", "spell_school": "Tiger Claw"}, {"spell_name": "Dazing Strike", "casting_time": "1 standard action", "spell_level": 5, "rulebook": "ToB", "duration": "1 round", "effect": "", "spell_range": "Melee attack", "components": "", "spell_school": "Iron Heart"}, {"spell_name": "Disrupting Blow", "casting_time": "1 standard action", "spell_level": 5, "rulebook": "ToB", "duration": "1 round", "effect": "", "spell_range": "Melee attack", "components": "", "spell_school": "Diamond Mind"}, {"spell_name": "Elder Mountain Hammer", "casting_time": "1 standard action", "spell_level": 5, "rulebook": "ToB", "duration": "", "effect": "", "spell_range": "Melee attack", "components": "", "spell_school": "Stone Dragon"}, {"spell_name": "Flanking Maneuver", "casting_time": "1 standard action", "spell_level": 5, "rulebook": "ToB", "duration": "", "effect": "", "spell_range": "Melee attack", "components": "", "spell_school": "White Raven"}, {"spell_name": "Giant's Stance", "casting_time": "1 swift action", "spell_level": 5, "rulebook": "ToB", "duration": "Stance", "effect": "", "spell_range": "Personal", "components": "", "spell_school": "Stone Dragon"}, {"spell_name": "Hearing the Air", "casting_time": "1 swift action", "spell_level": 5, "rulebook": "ToB", "duration": "Stance", "effect": "", "spell_range": "Personal", "components": "", "spell_school": "Diamond Mind"}, {"spell_name": "Iron Heart Focus", "casting_time": "1 immediate action", "spell_level": 5, "rulebook": "ToB", "duration": "", "effect": "", "spell_range": "Personal", "components": "", "spell_school": "Iron Heart"}, {"spell_name": "Mountain Avalanche", "casting_time": "1 full-round action", "spell_level": 5, "rulebook": "ToB", "duration": "", "effect": "", "spell_range": "Personal", "components": "", "spell_school": "Stone Dragon"}, {"spell_name": "Pouncing Charge", "casting_time": "1 full-round action", "spell_level": 5, "rulebook": "ToB", "duration": "", "effect": "", "spell_range": "Personal", "components": "", "spell_school": "Tiger Claw"}, {"spell_name": "Press the Advantage", "casting_time": "1 swift action", "spell_level": 5, "rulebook": "ToB", "duration": "Stance", "effect": "", "spell_range": "Personal", "components": "", "spell_school": "White Raven"}, {"spell_name": "Rapid Counter", "casting_time": "1 immediate action", "spell_level": 5, "rulebook": "ToB", "duration": "", "effect": "", "spell_range": "Personal", "components": "", "spell_school": "Diamond Mind"}, {"spell_name": "Crushing Vise", "casting_time": "1 standard action", "spell_level": 6, "rulebook": "ToB", "duration": "1 round", "effect": "", "spell_range": "Melee attack", "components": "", "spell_school": "Stone Dragon"}, {"spell_name": "Insightful Strike, Greater", "casting_time": "1 standard action", "spell_level": 6, "rulebook": "ToB", "duration": "", "effect": "", "spell_range": "Melee attack", "components": "", "spell_school": "Diamond Mind"}, {"spell_name": "Iron Bones", "casting_time": "1 standard action", "spell_level": 6, "rulebook": "ToB", "duration": "1 round", "effect": "", "spell_range": "Personal", "components": "", "spell_school": "Stone Dragon"}, {"spell_name": "Iron Heart Endurance", "casting_time": "1 swift action", "spell_level": 6, "rulebook": "ToB", "duration": "", "effect": "", "spell_range": "Personal", "components": "", "spell_school": "Iron Heart"}, {"spell_name": "Irresistible Mountain Strike", "casting_time": "1 standard action", "spell_level": 6, "rulebook": "ToB", "duration": "1 round", "effect": "", "spell_range": "Melee attack", "components": "", "spell_school": "Stone Dragon"}, {"spell_name": "Manticore Parry", "casting_time": "1 immediate action", "spell_level": 6, "rulebook": "ToB", "duration": "", "effect": "", "spell_range": "Personal", "components": "", "spell_school": "Iron Heart"}, {"spell_name": "Moment of Alacrity", "casting_time": "1 swift action", "spell_level": 6, "rulebook": "ToB", "duration": "Instantaneous", "effect": "", "spell_range": "Personal", "components": "", "spell_school": "Diamond Mind"}, {"spell_name": "Order Forged from Chaos", "casting_time": "1 move action", "spell_level": 6, "rulebook": "ToB", "duration": "", "effect": "", "spell_range": "Personal", "components": "", "spell_school": "White Raven"}, {"spell_name": "Rabid Bear Strike", "casting_time": "1 standard action", "spell_level": 6, "rulebook": "ToB", "duration": "", "effect": "", "spell_range": "Melee attack", "components": "", "spell_school": "Tiger Claw"}, {"spell_name": "War Leader's Charge", "casting_time": "1 full-round action", "spell_level": 6, "rulebook": "ToB", "duration": "", "effect": "", "spell_range": "Melee attack", "components": "", "spell_school": "White Raven"}, {"spell_name": "Wolf Climbs the Mountain", "casting_time": "1 full-round action", "spell_level": 6, "rulebook": "ToB", "duration": "", "effect": "", "spell_range": "Melee attack", "components": "", "spell_school": "Tiger Claw"}, {"spell_name": "Ancient Mountain Hammer", "casting_time": "1 standard action", "spell_level": 7, "rulebook": "ToB", "duration": "", "effect": "", "spell_range": "Melee attack", "components": "", "spell_school": "Stone Dragon"}, {"spell_name": "Avalanche of Blades", "casting_time": "1 full-round action", "spell_level": 7, "rulebook": "ToB", "duration": "", "effect": "", "spell_range": "Melee attack", "components": "", "spell_school": "Diamond Mind"}, {"spell_name": "Clarion Call", "casting_time": "1 swift action", "spell_level": 7, "rulebook": "ToB", "duration": "", "effect": "", "spell_range": "60 ft.", "components": "", "spell_school": "White Raven"}, {"spell_name": "Colossus Strike", "casting_time": "1 standard action", "spell_level": 7, "rulebook": "ToB", "duration": "", "effect": "", "spell_range": "Melee attack", "components": "", "spell_school": "Stone Dragon"}, {"spell_name": "Finishing Move", "casting_time": "1 standard action", "spell_level": 7, "rulebook": "ToB", "duration": "", "effect": "", "spell_range": "Melee attack", "components": "", "spell_school": "Iron Heart"}, {"spell_name": "Hamstring Attack", "casting_time": "1 standard action", "spell_level": 7, "rulebook": "ToB", "duration": "1 minute", "effect": "", "spell_range": "Melee attack", "components": "", "spell_school": "Tiger Claw"}, {"spell_name": "Prey on the Weak", "casting_time": "1 swift action", "spell_level": 7, "rulebook": "ToB", "duration": "Stance", "effect": "", "spell_range": "Personal", "components": "", "spell_school": "Tiger Claw"}, {"spell_name": "Quicksilver Motion", "casting_time": "1 swift action", "spell_level": 7, "rulebook": "ToB", "duration": "", "effect": "", "spell_range": "Personal", "components": "", "spell_school": "Diamond Mind"}, {"spell_name": "Scything Blade", "casting_time": "1 swift action", "spell_level": 7, "rulebook": "ToB", "duration": "", "effect": "", "spell_range": "Personal", "components": "", "spell_school": "Iron Heart"}, {"spell_name": "Swarming Assault", "casting_time": "1 standard action", "spell_level": 7, "rulebook": "ToB", "duration": "", "effect": "", "spell_range": "Melee attack", "components": "", "spell_school": "White Raven"}, {"spell_name": "Swooping Dragon Strike", "casting_time": "1 standard action", "spell_level": 7, "rulebook": "ToB", "duration": "", "effect": "", "spell_range": "Melee attack", "components": "", "spell_school": "Tiger Claw"}, {"spell_name": "Adamantine Bones", "casting_time": "1 standard action", "spell_level": 8, "rulebook": "ToB", "duration": "1 round", "effect": "", "spell_range": "Personal", "components": "", "spell_school": "Stone Dragon"}, {"spell_name": "Adamantine Hurricane", "casting_time": "1 standard action", "spell_level": 8, "rulebook": "ToB", "duration": "", "effect": "", "spell_range": "Melee attack", "components": "", "spell_school": "Iron Heart"}, {"spell_name": "Diamond Defense", "casting_time": "1 immediate action", "spell_level": 8, "rulebook": "ToB", "duration": "", "effect": "", "spell_range": "Personal", "components": "", "spell_school": "Diamond Mind"}, {"spell_name": "Diamond Nightmare Blade", "casting_time": "1 standard action", "spell_level": 8, "rulebook": "ToB", "duration": "", "effect": "", "spell_range": "Melee attack", "components": "", "spell_school": "Diamond Mind"}, {"spell_name": "Earthstrike Quake", "casting_time": "1 standard action", "spell_level": 8, "rulebook": "ToB", "duration": "Instantaneous", "effect": "", "spell_range": "20 ft.", "components": "", "spell_school": "Stone Dragon"}, {"spell_name": "Girallon Windmill Flesh Rip", "casting_time": "1 swift action", "spell_level": 8, "rulebook": "ToB", "duration": "End of turn", "effect": "", "spell_range": "Melee attack", "components": "", "spell_school": "Tiger Claw"}, {"spell_name": "Lightning Throw", "casting_time": "1 standard action", "spell_level": 8, "rulebook": "ToB", "duration": "Instantaneous", "effect": "", "spell_range": "30 ft.", "components": "", "spell_school": "Iron Heart"}, {"spell_name": "Raging Mongoose", "casting_time": "1 swift action", "spell_level": 8, "rulebook": "ToB", "duration": "End of turn", "effect": "", "spell_range": "Personal", "components": "", "spell_school": "Tiger Claw"}, {"spell_name": "Stance of Alacrity", "casting_time": "1 swift action", "spell_level": 8, "rulebook": "ToB", "duration": "Stance", "effect": "", "spell_range": "Personal", "components": "", "spell_school": "Diamond Mind"}, {"spell_name": "Strength of Stone", "casting_time": "1 swift action", "spell_level": 8, "rulebook": "ToB", "duration": "Stance", "effect": "", "spell_range": "Personal", "components": "", "spell_school": "Stone Dragon"}, {"spell_name": "Supreme Blade Parry", "casting_time": "1 swift action", "spell_level": 8, "rulebook": "ToB", "duration": "Stance", "effect": "", "spell_range": "Personal", "components": "", "spell_school": "Iron Heart"}, {"spell_name": "Swarm Tactics", "casting_time": "1 swift action", "spell_level": 8, "rulebook": "ToB", "duration": "Stance", "effect": "", "spell_range": "60 ft.", "components": "", "spell_school": "White Raven"}, {"spell_name": "White Raven Hammer", "casting_time": "1 standard action", "spell_level": 8, "rulebook": "ToB", "duration": "1 round", "effect": "", "spell_range": "Melee attack", "components": "", "spell_school": "White Raven"}, {"spell_name": "Wolf Pack Tactics", "casting_time": "1 swift action", "spell_level": 8, "rulebook": "ToB", "duration": "Stance", "effect": "", "spell_range": "Personal", "components": "", "spell_school": "Tiger Claw"}, {"spell_name": "Feral Death Blow", "casting_time": "1 full-round action", "spell_level": 9, "rulebook": "ToB", "duration": "", "effect": "", "spell_range": "Melee attack", "components": "", "spell_school": "Tiger Claw"}, {"spell_name": "Mountain Tombstone Strike", "casting_time": "1 standard action", "spell_level": 9, "rulebook": "ToB", "duration": "", "effect": "", "spell_range": "Melee attack", "components": "", "spell_school": "Stone Dragon"}, {"spell_name": "Strike of Perfect Clarity", "casting_time": "1 standard action", "spell_level": 9, "rulebook": "ToB", "duration": "", "effect": "", "spell_range": "Melee attack", "components": "", "spell_school": "Iron Heart"}, {"spell_name": "Time Stands Still", "casting_time": "1 full-round action", "spell_level": 9, "rulebook": "ToB", "duration": "", "effect": "", "spell_range": "Personal", "components": "", "spell_school": "Diamond Mind"}, {"spell_name": "War Master's Charge", "casting_time": "1 full-round action", "spell_level": 9, "rulebook": "ToB", "duration": "", "effect": "", "spell_range": "Melee attack; see text", "components": "", "spell_school": "White Raven"}]